pytest_logikal/__init__.py
pytest_logikal/bandit.py
pytest_logikal/bandit_config.yml
pytest_logikal/black.py
pytest_logikal/browser.py
pytest_logikal/build.py
pytest_logikal/core.py
pytest_logikal/css.py
pytest_logikal/css_config.yml
pytest_logikal/django.py
pytest_logikal/docs.py
pytest_logikal/file_checker.py
pytest_logikal/html.py
pytest_logikal/isort.py
pytest_logikal/js.py
pytest_logikal/js_config.mjs
pytest_logikal/licenses.py
pytest_logikal/migration.py
pytest_logikal/node_install.py
pytest_logikal/package-lock.json
pytest_logikal/package.json
pytest_logikal/plugin.py
pytest_logikal/py.typed
pytest_logikal/pylint.py
pytest_logikal/requirements.py
pytest_logikal/spell.py
pytest_logikal/style.py
pytest_logikal/svg.py
pytest_logikal/translations.py
pytest_logikal/utils.py
pytest_logikal/validator.py
pytest_logikal-6.0.3.dist-info/licenses/LICENSE.txt
pytest_logikal-6.0.3.dist-info/METADATA
pytest_logikal-6.0.3.dist-info/WHEEL
pytest_logikal-6.0.3.dist-info/entry_points.txt
pytest_logikal-6.0.3.dist-info/top_level.txt
pytest_logikal-6.0.3.dist-info/RECORD
