Metadata-Version: 2.4
Name: pytest-logikal
Version: 6.0.3
Summary: Common testing environment
Author-email: Logikal GmbH <contact@logikal.io>
License-Expression: MIT
Project-URL: Documentation, https://docs.logikal.io/pytest-logikal/
Project-URL: Release notes, https://github.com/logikal-io/pytest-logikal/releases
Project-URL: Issue tracker, https://github.com/logikal-io/pytest-logikal/issues
Project-URL: Source code, https://github.com/logikal-io/pytest-logikal
Keywords: pytest
Classifier: Development Status :: 5 - Production/Stable
Classifier: Intended Audience :: Developers
Classifier: Operating System :: POSIX :: Linux
Classifier: Programming Language :: Python :: 3
Classifier: Programming Language :: Python :: 3.12
Classifier: Framework :: Pytest
Classifier: Topic :: Software Development
Classifier: Typing :: Typed
Requires-Python: ~=3.12
License-File: LICENSE.txt
Requires-Dist: bandit==1.9.3
Requires-Dist: codespell==2.4.1
Requires-Dist: coverage==7.13.1
Requires-Dist: isort[colors]==7.0.0
Requires-Dist: mypy[faster-cache]==1.19.1
Requires-Dist: license-expression==30.4.4
Requires-Dist: pycodestyle==2.14.0
Requires-Dist: pydocstyle==6.3.0
Requires-Dist: pylint==4.0.4
Requires-Dist: pytest==9.0.2
Requires-Dist: pytest-cov==7.0.0
Requires-Dist: pytest-mock==3.15.1
Requires-Dist: pytest-mypy==1.0.1
Requires-Dist: pytest-xdist[psutil]==3.8.0
Requires-Dist: logikal-utils~=1.5
Requires-Dist: pyorbs~=2.1
Requires-Dist: termcolor~=3.3
Provides-Extra: black
Requires-Dist: black==26.1.0; extra == "black"
Provides-Extra: browser
Requires-Dist: logikal-browser~=3.1; extra == "browser"
Provides-Extra: django
Requires-Dist: babel~=2.17; extra == "django"
Requires-Dist: Django<7,>=5.2; extra == "django"
Requires-Dist: django-stubs<7,>=5.2; extra == "django"
Requires-Dist: django-migration-linter~=6.0; extra == "django"
Requires-Dist: djlint==1.36.4; extra == "django"
Requires-Dist: logikal-browser[django]~=3.0; extra == "django"
Requires-Dist: pylint-django==2.7.0; extra == "django"
Requires-Dist: pytest-django==4.11.1; extra == "django"
Requires-Dist: pytest-factoryboy==2.8.1; extra == "django"
Requires-Dist: requests~=2.32; extra == "django"
Requires-Dist: logikal-utils[docker]~=1.5; extra == "django"
Dynamic: license-file
